pycentroid/client/README.md
pycentroid/client/__init__.py
pycentroid/client/client.py
pycentroid/client/metadata.py
pycentroid/client/sql.py
pycentroid/common/__init__.py
pycentroid/common/application.py
pycentroid/common/configuration.py
pycentroid/common/datetime.py
pycentroid/common/events.py
pycentroid/common/exceptions.py
pycentroid/common/expect.py
pycentroid/common/objects.py
pycentroid/data/__init__.py
pycentroid/data/application.py
pycentroid/data/configuration.py
pycentroid/data/context.py
pycentroid/data/data_types.py
pycentroid/data/functions.py
pycentroid/data/listeners/__init__.py
pycentroid/data/listeners/expand.py
pycentroid/data/listeners/validator.py
pycentroid/data/loaders.py
pycentroid/data/model.py
pycentroid/data/queryable.py
pycentroid/data/resources/dataTypes.json
pycentroid/data/resources/models/Migration.json
pycentroid/data/types.py
pycentroid/data/upgrade.py
pycentroid/query/__init__.py
pycentroid/query/closure_parser.py
pycentroid/query/data_objects.py
pycentroid/query/method_parser.py
pycentroid/query/object_name_validator.py
pycentroid/query/open_data_formatter.py
pycentroid/query/open_data_parser.py
pycentroid/query/open_data_query.py
pycentroid/query/query_entity.py
pycentroid/query/query_expression.py
pycentroid/query/query_field.py
pycentroid/query/query_value.py
pycentroid/query/resolvers.py
pycentroid/query/sql_formatter.py
pycentroid/query/utils.py
pycentroid/sqlite/__init__.py
pycentroid/sqlite/adapter.py
pycentroid/sqlite/dialect.py
pycentroid-2.0.0.dist-info/LICENSE.txt
pycentroid-2.0.0.dist-info/METADATA
pycentroid-2.0.0.dist-info/WHEEL
pycentroid-2.0.0.dist-info/RECORD
