Metadata-Version: 2.1
Name: pycentroid
Version: 2.0.0
Summary: @themost-framework alternative for python
Author: Kyriakos Barbounakis
Author-email: k.barbounakis@gmail.com
Requires-Python: >=3.9,<4.0
Classifier: Programming Language :: Python :: 3
Classifier: Programming Language :: Python :: 3.9
Classifier: Programming Language :: Python :: 3.10
Classifier: Programming Language :: Python :: 3.11
Classifier: Programming Language :: Python :: 3.12
Classifier: Programming Language :: Python :: 3.13
Requires-Dist: asyncio (>=3.4.3,<4.0.0)
Requires-Dist: dill (>=0.3.6,<0.4.0)
Requires-Dist: inflect (>=7.0.0,<8.0.0)
Requires-Dist: pydash (>=7.0.0,<8.0.0)
Requires-Dist: python-dateutil (>=2.8.2,<3.0.0)
Requires-Dist: pyyaml (>=6.0,<7.0)
Requires-Dist: requests (==2.32.0)
Requires-Dist: requests-async (>=0.6.2,<0.7.0)
Requires-Dist: sqlglot (>=18.10.1,<19.0.0)
Requires-Dist: typing-extensions (>=4.5.0,<5.0.0)
Requires-Dist: urllib3 (==2.2.2)
